{
  "formatVersion": "1.1",
  "component": {
    "group": "com.cgi.glk.ectp",
    "module": "ectpcommon",
    "version": "1.0",
    "attributes": {
      "org.gradle.status": "release"
    }
  },
  "createdBy": {
    "gradle": {
      "version": "7.1"
    }
  },
  "variants": [
    {
      "name": "apiElements",
      "attributes": {
        "org.gradle.category": "library",
        "org.gradle.dependency.bundling": "external",
        "org.gradle.jvm.version": 11,
        "org.gradle.libraryelements": "jar",
        "org.gradle.usage": "java-api"
      },
      "files": [
        {
          "name": "ectpcommon-1.0.jar",
          "url": "ectpcommon-1.0.jar",
          "size": 12604,
          "sha512": "774fc8488aa00950f3e6d21312cd5abca6cdac0224ae89535e7387a0ce6208b63b3dc2fb09c02ae4d9ba7edf1ae47f9254d5906fb4ff422db02c22a5b9e82363",
          "sha256": "3e586588dbbd4feda27e0dfdfb002920954dddaef0f1d19dca2ff1c239145ba3",
          "sha1": "75ae85e2acb338ab27fc3d597afe5cd38ec65147",
          "md5": "3f09c565402ed6360d08147ba3d138b8"
        }
      ]
    },
    {
      "name": "runtimeElements",
      "attributes": {
        "org.gradle.category": "library",
        "org.gradle.dependency.bundling": "external",
        "org.gradle.jvm.version": 11,
        "org.gradle.libraryelements": "jar",
        "org.gradle.usage": "java-runtime"
      },
      "dependencies": [
        {
          "group": "com.auth0",
          "module": "java-jwt",
          "version": {
            "requires": "3.18.1"
          }
        },
        {
          "group": "org.springframework.cloud",
          "module": "spring-cloud-starter-openfeign",
          "version": {
            "requires": "3.0.6"
          }
        }
      ],
      "files": [
        {
          "name": "ectpcommon-1.0.jar",
          "url": "ectpcommon-1.0.jar",
          "size": 12604,
          "sha512": "774fc8488aa00950f3e6d21312cd5abca6cdac0224ae89535e7387a0ce6208b63b3dc2fb09c02ae4d9ba7edf1ae47f9254d5906fb4ff422db02c22a5b9e82363",
          "sha256": "3e586588dbbd4feda27e0dfdfb002920954dddaef0f1d19dca2ff1c239145ba3",
          "sha1": "75ae85e2acb338ab27fc3d597afe5cd38ec65147",
          "md5": "3f09c565402ed6360d08147ba3d138b8"
        }
      ]
    }
  ]
}
